pyramid_di/__init__.py
pyramid_di-0.4.2.dist-info/METADATA
pyramid_di-0.4.2.dist-info/WHEEL
pyramid_di-0.4.2.dist-info/top_level.txt
pyramid_di-0.4.2.dist-info/RECORD
