Metadata-Version: 2.1
Name: pyramid-di
Version: 0.4.2
Summary: Dependency injection stuff for Pyramid
Home-page: http://github.com/tetframework/pyramid_di
Author: Antti Haapala
Author-email: antti.haapala@anttipatterns.com
Keywords: web wsgi bfg pylons pyramid
Classifier: Development Status :: 4 - Beta
Classifier: Framework :: Pyramid
Classifier: Intended Audience :: Developers
Classifier: License :: OSI Approved :: Python Software Foundation License
Classifier: Programming Language :: Python :: 3.6
Classifier: Programming Language :: Python :: 3.7
Classifier: Programming Language :: Python :: 3.8
Classifier: Programming Language :: Python :: 3.9
Classifier: Programming Language :: Python :: 3.10
Classifier: Programming Language :: Python :: 3.11
Classifier: Programming Language :: Python :: 3 :: Only
Classifier: Topic :: Internet :: WWW/HTTP :: WSGI
Classifier: Topic :: Internet :: WWW/HTTP :: WSGI :: Application
Classifier: Topic :: Internet :: WWW/HTTP :: WSGI :: Middleware
Classifier: Topic :: Software Development :: Libraries :: Application Frameworks
Requires-Dist: pyramid (<3.0,>=1.7)
Requires-Dist: pyramid-services (<2.0,>=1.1)
Provides-Extra: dev
Requires-Dist: pytest (>=3.0) ; extra == 'dev'
Requires-Dist: pytest-cov ; extra == 'dev'
